django_tidb/__init__.py
django_tidb/base.py
django_tidb/features.py
django_tidb/introspection.py
django_tidb/operations.py
django_tidb/patch.py
django_tidb/schema.py
django_tidb/version.py
django_tidb/fields/__init__.py
django_tidb/fields/vector.py
django_tidb-6.0.0.dist-info/licenses/LICENSE
django_tidb-6.0.0.dist-info/METADATA
django_tidb-6.0.0.dist-info/WHEEL
django_tidb-6.0.0.dist-info/top_level.txt
django_tidb-6.0.0.dist-info/RECORD
