Metadata-Version: 2.4
Name: django-tidb
Version: 6.0.0
Summary: Django backend for TiDB
Author-email: Xiang Zhang <zhangxiang02@pingcap.com>, Di Wang <wangdi@pingcap.com>
Project-URL: Homepage, https://github.com/pingcap/tidb
Project-URL: Bug Reports, https://github.com/pingcap/django-tidb/issues
Project-URL: Source, https://github.com/pingcap/django-tidb
Classifier: Development Status :: 5 - Production/Stable
Classifier: Framework :: Django
Classifier: Framework :: Django :: 6.0
Classifier: License :: OSI Approved :: Apache Software License
Classifier: Operating System :: OS Independent
Classifier: Programming Language :: Python
Classifier: Programming Language :: Python :: 3
Classifier: Programming Language :: Python :: 3.12
Classifier: Programming Language :: Python :: 3.13
Classifier: Programming Language :: Python :: 3.14
Requires-Python: >=3.12
License-File: LICENSE
Provides-Extra: vector
Requires-Dist: numpy<3,>=1; extra == "vector"
Dynamic: license-file
